slmcontrol/__init__.py
slmcontrol/hologram.py
slmcontrol/slm.py
slmcontrol/structures.py
slmcontrol/zernike.py
slmcontrol-0.2.0.dist-info/METADATA
slmcontrol-0.2.0.dist-info/WHEEL
slmcontrol-0.2.0.dist-info/licenses/LICENSE
slmcontrol-0.2.0.dist-info/RECORD
