Metadata-Version: 2.4
Name: slmcontrol
Version: 0.2.0
Summary: Add your description here
Author-email: Marcos Gil <marcosgildeoliveira@gmail.com>
License-File: LICENSE
Requires-Python: >=3.10
Requires-Dist: juliacall>=0.9.23
Requires-Dist: juliapkg>=0.1.14
Requires-Dist: numpy>=1.25
